<?xml version="1.0" encoding="UTF-8"?>
<!DOCTYPE plist PUBLIC "-//Apple//DTD PLIST 1.0//EN" "http://www.apple.com/DTDs/PropertyList-1.0.dtd"/>

<plist version="1.0">
    <dict>
        <key>ROOT</key>
        <array>
            <dict>
                <key>id</key>
                <string>147</string>
                <key>className</key>
                <string>PTModelAnimation</string>
                <key>Name</key>
                <dict>
                    <key>value</key>
                    <string></string>
                </dict>
                <key>duration</key>
                <string>0.033333</string>
                <key>animationSpeed</key>
                <string>1.000000</string>
                <key>looped</key>
                <string>1</string>
            </dict>
            <dict>
                <key>id</key>
                <string>156</string>
                <key>className</key>
                <string>PTModelAnimation</string>
                <key>Name</key>
                <dict>
                    <key>value</key>
                    <string></string>
                </dict>
                <key>duration</key>
                <string>0.033333</string>
                <key>animationSpeed</key>
                <string>1.000000</string>
                <key>looped</key>
                <string>1</string>
            </dict>
            <dict>
                <key>id</key>
                <string>168</string>
                <key>className</key>
                <string>PTModelAnimation</string>
                <key>Name</key>
                <dict>
                    <key>value</key>
                    <string></string>
                </dict>
                <key>duration</key>
                <string>0.033333</string>
                <key>animationSpeed</key>
                <string>1.000000</string>
                <key>looped</key>
                <string>1</string>
            </dict>
            <dict>
                <key>id</key>
                <string>210</string>
                <key>className</key>
                <string>PTModelAnimation</string>
                <key>Name</key>
                <dict>
                    <key>value</key>
                    <string></string>
                </dict>
                <key>duration</key>
                <string>0.033333</string>
                <key>animationSpeed</key>
                <string>1.000000</string>
                <key>looped</key>
                <string>1</string>
            </dict>
            <dict>
                <key>id</key>
                <string>221</string>
                <key>className</key>
                <string>PTModelAnimation</string>
                <key>Name</key>
                <dict>
                    <key>value</key>
                    <string></string>
                </dict>
                <key>duration</key>
                <string>0.033333</string>
                <key>animationSpeed</key>
                <string>1.000000</string>
                <key>looped</key>
                <string>1</string>
            </dict>
            <dict>
                <key>id</key>
                <string>232</string>
                <key>className</key>
                <string>PTModelAnimation</string>
                <key>Name</key>
                <dict>
                    <key>value</key>
                    <string></string>
                </dict>
                <key>duration</key>
                <string>0.033333</string>
                <key>animationSpeed</key>
                <string>1.000000</string>
                <key>looped</key>
                <string>1</string>
            </dict>
            <dict>
                <key>id</key>
                <string>260</string>
                <key>className</key>
                <string>PTModelAnimation</string>
                <key>Name</key>
                <dict>
                    <key>value</key>
                    <string></string>
                </dict>
                <key>duration</key>
                <string>0.033333</string>
                <key>animationSpeed</key>
                <string>1.000000</string>
                <key>looped</key>
                <string>1</string>
            </dict>
            <dict>
                <key>id</key>
                <string>379</string>
                <key>className</key>
                <string>PTModelAnimation</string>
                <key>Name</key>
                <dict>
                    <key>value</key>
                    <string></string>
                </dict>
                <key>duration</key>
                <string>0.033333</string>
                <key>animationSpeed</key>
                <string>1.000000</string>
                <key>looped</key>
                <string>1</string>
            </dict>
            <dict>
                <key>id</key>
                <string>394</string>
                <key>className</key>
                <string>PTModelAnimation</string>
                <key>Name</key>
                <dict>
                    <key>value</key>
                    <string></string>
                </dict>
                <key>duration</key>
                <string>0.033333</string>
                <key>animationSpeed</key>
                <string>1.000000</string>
                <key>looped</key>
                <string>1</string>
            </dict>
            <dict>
                <key>id</key>
                <string>409</string>
                <key>className</key>
                <string>PTModelAnimation</string>
                <key>Name</key>
                <dict>
                    <key>value</key>
                    <string></string>
                </dict>
                <key>duration</key>
                <string>0.033333</string>
                <key>animationSpeed</key>
                <string>1.000000</string>
                <key>looped</key>
                <string>1</string>
            </dict>
            <dict>
                <key>id</key>
                <string>416</string>
                <key>className</key>
                <string>PTModelAnimation</string>
                <key>Name</key>
                <dict>
                    <key>value</key>
                    <string></string>
                </dict>
                <key>duration</key>
                <string>3.000000</string>
                <key>animationSpeed</key>
                <string>1.000000</string>
                <key>looped</key>
                <string>1</string>
            </dict>
            <dict>
                <key>id</key>
                <string>441</string>
                <key>className</key>
                <string>PTModelAnimation</string>
                <key>Name</key>
                <dict>
                    <key>value</key>
                    <string></string>
                </dict>
                <key>duration</key>
                <string>3.000000</string>
                <key>animationSpeed</key>
                <string>1.000000</string>
                <key>looped</key>
                <string>1</string>
            </dict>
            <dict>
                <key>id</key>
                <string>450</string>
                <key>className</key>
                <string>PTModelAnimation</string>
                <key>Name</key>
                <dict>
                    <key>value</key>
                    <string></string>
                </dict>
                <key>duration</key>
                <string>0.033333</string>
                <key>animationSpeed</key>
                <string>1.000000</string>
                <key>looped</key>
                <string>1</string>
            </dict>
            <dict>
                <key>id</key>
                <string>500</string>
                <key>className</key>
                <string>PTModelAnimation</string>
                <key>Name</key>
                <dict>
                    <key>value</key>
                    <string></string>
                </dict>
                <key>duration</key>
                <string>0.033333</string>
                <key>animationSpeed</key>
                <string>1.000000</string>
                <key>looped</key>
                <string>1</string>
            </dict>
            <dict>
                <key>id</key>
                <string>949</string>
                <key>className</key>
                <string>PTModelAnimation</string>
                <key>Name</key>
                <dict>
                    <key>value</key>
                    <string></string>
                </dict>
                <key>duration</key>
                <string>3.000000</string>
                <key>animationSpeed</key>
                <string>1.000000</string>
                <key>looped</key>
                <string>1</string>
            </dict>
            <dict>
                <key>id</key>
                <string>975</string>
                <key>className</key>
                <string>PTModelAnimation</string>
                <key>Name</key>
                <dict>
                    <key>value</key>
                    <string></string>
                </dict>
                <key>duration</key>
                <string>3.000000</string>
                <key>animationSpeed</key>
                <string>1.000000</string>
                <key>looped</key>
                <string>1</string>
            </dict>
            <dict>
                <key>id</key>
                <string>1009</string>
                <key>className</key>
                <string>PTModelAnimation</string>
                <key>Name</key>
                <dict>
                    <key>value</key>
                    <string></string>
                </dict>
                <key>duration</key>
                <string>3.000000</string>
                <key>animationSpeed</key>
                <string>1.000000</string>
                <key>looped</key>
                <string>1</string>
            </dict>
            <dict>
                <key>id</key>
                <string>1207</string>
                <key>className</key>
                <string>PTModelAnimation</string>
                <key>Name</key>
                <dict>
                    <key>value</key>
                    <string></string>
                </dict>
                <key>duration</key>
                <string>0.033333</string>
                <key>animationSpeed</key>
                <string>1.000000</string>
                <key>looped</key>
                <string>1</string>
            </dict>
            <dict>
                <key>id</key>
                <string>1219</string>
                <key>className</key>
                <string>PTModelAnimation</string>
                <key>Name</key>
                <dict>
                    <key>value</key>
                    <string></string>
                </dict>
                <key>duration</key>
                <string>0.033333</string>
                <key>animationSpeed</key>
                <string>1.000000</string>
                <key>looped</key>
                <string>1</string>
            </dict>
            <dict>
                <key>id</key>
                <string>1282</string>
                <key>className</key>
                <string>PTModelAnimation</string>
                <key>Name</key>
                <dict>
                    <key>value</key>
                    <string></string>
                </dict>
                <key>duration</key>
                <string>0.200000</string>
                <key>animationSpeed</key>
                <string>1.000000</string>
                <key>looped</key>
                <string>1</string>
            </dict>
            <dict>
                <key>id</key>
                <string>1389</string>
                <key>className</key>
                <string>PTModelAnimation</string>
                <key>Name</key>
                <dict>
                    <key>value</key>
                    <string></string>
                </dict>
                <key>duration</key>
                <string>0.733333</string>
                <key>animationSpeed</key>
                <string>1.000000</string>
                <key>looped</key>
                <string>1</string>
            </dict>
            <dict>
                <key>id</key>
                <string>1459</string>
                <key>className</key>
                <string>PTModelAnimation</string>
                <key>Name</key>
                <dict>
                    <key>value</key>
                    <string></string>
                </dict>
                <key>duration</key>
                <string>0.200000</string>
                <key>animationSpeed</key>
                <string>1.000000</string>
                <key>looped</key>
                <string>1</string>
            </dict>
            <dict>
                <key>id</key>
                <string>1651</string>
                <key>className</key>
                <string>PTModelAnimation</string>
                <key>Name</key>
                <dict>
                    <key>value</key>
                    <string></string>
                </dict>
                <key>duration</key>
                <string>0.200000</string>
                <key>animationSpeed</key>
                <string>1.000000</string>
                <key>looped</key>
                <string>1</string>
            </dict>
            <dict>
                <key>id</key>
                <string>1665</string>
                <key>className</key>
                <string>PTModelAnimation</string>
                <key>Name</key>
                <dict>
                    <key>value</key>
                    <string></string>
                </dict>
                <key>duration</key>
                <string>0.033333</string>
                <key>animationSpeed</key>
                <string>1.000000</string>
                <key>looped</key>
                <string>1</string>
            </dict>
            <dict>
                <key>id</key>
                <string>1685</string>
                <key>className</key>
                <string>PTModelAnimation</string>
                <key>Name</key>
                <dict>
                    <key>value</key>
                    <string></string>
                </dict>
                <key>duration</key>
                <string>0.300000</string>
                <key>animationSpeed</key>
                <string>1.000000</string>
                <key>looped</key>
                <string>1</string>
            </dict>
            <dict>
                <key>id</key>
                <string>1697</string>
                <key>className</key>
                <string>PTModelAnimation</string>
                <key>Name</key>
                <dict>
                    <key>value</key>
                    <string></string>
                </dict>
                <key>duration</key>
                <string>0.033333</string>
                <key>animationSpeed</key>
                <string>1.000000</string>
                <key>looped</key>
                <string>1</string>
            </dict>
            <dict>
                <key>id</key>
                <string>1709</string>
                <key>className</key>
                <string>PTModelAnimation</string>
                <key>Name</key>
                <dict>
                    <key>value</key>
                    <string></string>
                </dict>
                <key>duration</key>
                <string>0.033333</string>
                <key>animationSpeed</key>
                <string>1.000000</string>
                <key>looped</key>
                <string>1</string>
            </dict>
            <dict>
                <key>id</key>
                <string>1834</string>
                <key>className</key>
                <string>PTModelAnimation</string>
                <key>Name</key>
                <dict>
                    <key>value</key>
                    <string></string>
                </dict>
                <key>duration</key>
                <string>0.133333</string>
                <key>animationSpeed</key>
                <string>0.400000</string>
                <key>looped</key>
                <string>1</string>
            </dict>
            <dict>
                <key>id</key>
                <string>1899</string>
                <key>className</key>
                <string>PTModelAnimation</string>
                <key>Name</key>
                <dict>
                    <key>value</key>
                    <string></string>
                </dict>
                <key>duration</key>
                <string>0.033333</string>
                <key>animationSpeed</key>
                <string>1.000000</string>
                <key>looped</key>
                <string>1</string>
            </dict>
            <dict>
                <key>id</key>
                <string>2077</string>
                <key>className</key>
                <string>PTModelAnimation</string>
                <key>Name</key>
                <dict>
                    <key>value</key>
                    <string></string>
                </dict>
                <key>duration</key>
                <string>0.666667</string>
                <key>animationSpeed</key>
                <string>1.000000</string>
                <key>looped</key>
                <string>1</string>
            </dict>
            <dict>
                <key>id</key>
                <string>2126</string>
                <key>className</key>
                <string>PTModelAnimation</string>
                <key>Name</key>
                <dict>
                    <key>value</key>
                    <string></string>
                </dict>
                <key>duration</key>
                <string>0.666667</string>
                <key>animationSpeed</key>
                <string>1.000000</string>
                <key>looped</key>
                <string>1</string>
            </dict>
            <dict>
                <key>id</key>
                <string>2197</string>
                <key>className</key>
                <string>PTModelAnimation</string>
                <key>Name</key>
                <dict>
                    <key>value</key>
                    <string></string>
                </dict>
                <key>duration</key>
                <string>0.666667</string>
                <key>animationSpeed</key>
                <string>1.000000</string>
                <key>looped</key>
                <string>1</string>
            </dict>
            <dict>
                <key>id</key>
                <string>2226</string>
                <key>className</key>
                <string>PTModelAnimation</string>
                <key>Name</key>
                <dict>
                    <key>value</key>
                    <string></string>
                </dict>
                <key>duration</key>
                <string>0.033333</string>
                <key>animationSpeed</key>
                <string>1.000000</string>
                <key>looped</key>
                <string>1</string>
            </dict>
            <dict>
                <key>id</key>
                <string>2288</string>
                <key>className</key>
                <string>PTModelAnimation</string>
                <key>Name</key>
                <dict>
                    <key>value</key>
                    <string></string>
                </dict>
                <key>duration</key>
                <string>0.400000</string>
                <key>animationSpeed</key>
                <string>0.200000</string>
                <key>looped</key>
                <string>0</string>
            </dict>
            <dict>
                <key>id</key>
                <string>2550</string>
                <key>className</key>
                <string>PTModelAnimation</string>
                <key>Name</key>
                <dict>
                    <key>value</key>
                    <string></string>
                </dict>
                <key>duration</key>
                <string>0.033333</string>
                <key>animationSpeed</key>
                <string>1.000000</string>
                <key>looped</key>
                <string>1</string>
            </dict>
            <dict>
                <key>id</key>
                <string>2566</string>
                <key>className</key>
                <string>PTModelAnimation</string>
                <key>Name</key>
                <dict>
                    <key>value</key>
                    <string></string>
                </dict>
                <key>duration</key>
                <string>0.033333</string>
                <key>animationSpeed</key>
                <string>1.000000</string>
                <key>looped</key>
                <string>1</string>
            </dict>
            <dict>
                <key>id</key>
                <string>2644</string>
                <key>className</key>
                <string>PTModelAnimation</string>
                <key>Name</key>
                <dict>
                    <key>value</key>
                    <string></string>
                </dict>
                <key>duration</key>
                <string>3.000000</string>
                <key>animationSpeed</key>
                <string>1.000000</string>
                <key>looped</key>
                <string>1</string>
            </dict>
            <dict>
                <key>id</key>
                <string>2675</string>
                <key>className</key>
                <string>PTModelAnimation</string>
                <key>Name</key>
                <dict>
                    <key>value</key>
                    <string></string>
                </dict>
                <key>duration</key>
                <string>0.133333</string>
                <key>animationSpeed</key>
                <string>1.000000</string>
                <key>looped</key>
                <string>1</string>
            </dict>
            <dict>
                <key>id</key>
                <string>2696</string>
                <key>className</key>
                <string>PTModelAnimation</string>
                <key>Name</key>
                <dict>
                    <key>value</key>
                    <string></string>
                </dict>
                <key>duration</key>
                <string>0.133333</string>
                <key>animationSpeed</key>
                <string>0.400000</string>
                <key>looped</key>
                <string>0</string>
            </dict>
            <dict>
                <key>id</key>
                <string>2713</string>
                <key>className</key>
                <string>PTModelAnimation</string>
                <key>Name</key>
                <dict>
                    <key>value</key>
                    <string></string>
                </dict>
                <key>duration</key>
                <string>0.133333</string>
                <key>animationSpeed</key>
                <string>1.000000</string>
                <key>looped</key>
                <string>1</string>
            </dict>
            <dict>
                <key>id</key>
                <string>2829</string>
                <key>className</key>
                <string>PTModelAnimation</string>
                <key>Name</key>
                <dict>
                    <key>value</key>
                    <string></string>
                </dict>
                <key>duration</key>
                <string>0.666667</string>
                <key>animationSpeed</key>
                <string>1.000000</string>
                <key>looped</key>
                <string>1</string>
            </dict>
            <dict>
                <key>id</key>
                <string>2972</string>
                <key>className</key>
                <string>PTModelAnimation</string>
                <key>Name</key>
                <dict>
                    <key>value</key>
                    <string></string>
                </dict>
                <key>duration</key>
                <string>0.666667</string>
                <key>animationSpeed</key>
                <string>1.000000</string>
                <key>looped</key>
                <string>1</string>
            </dict>
            <dict>
                <key>id</key>
                <string>3439</string>
                <key>className</key>
                <string>PTModelAnimation</string>
                <key>Name</key>
                <dict>
                    <key>value</key>
                    <string></string>
                </dict>
                <key>duration</key>
                <string>0.500000</string>
                <key>animationSpeed</key>
                <string>1.000000</string>
                <key>looped</key>
                <string>1</string>
            </dict>
            <dict>
                <key>id</key>
                <string>3500</string>
                <key>className</key>
                <string>PTModelAnimation</string>
                <key>Name</key>
                <dict>
                    <key>value</key>
                    <string></string>
                </dict>
                <key>duration</key>
                <string>0.033333</string>
                <key>animationSpeed</key>
                <string>0.500000</string>
                <key>looped</key>
                <string>0</string>
            </dict>
            <dict>
                <key>id</key>
                <string>3511</string>
                <key>className</key>
                <string>PTModelAnimation</string>
                <key>Name</key>
                <dict>
                    <key>value</key>
                    <string></string>
                </dict>
                <key>duration</key>
                <string>0.033333</string>
                <key>animationSpeed</key>
                <string>1.000000</string>
                <key>looped</key>
                <string>1</string>
            </dict>
            <dict>
                <key>id</key>
                <string>3544</string>
                <key>className</key>
                <string>PTModelAnimation</string>
                <key>Name</key>
                <dict>
                    <key>value</key>
                    <string></string>
                </dict>
                <key>duration</key>
                <string>0.200000</string>
                <key>animationSpeed</key>
                <string>0.500000</string>
                <key>looped</key>
                <string>0</string>
            </dict>
            <dict>
                <key>id</key>
                <string>3640</string>
                <key>className</key>
                <string>PTModelAnimation</string>
                <key>Name</key>
                <dict>
                    <key>value</key>
                    <string></string>
                </dict>
                <key>duration</key>
                <string>0.033333</string>
                <key>animationSpeed</key>
                <string>1.000000</string>
                <key>looped</key>
                <string>1</string>
            </dict>
            <dict>
                <key>id</key>
                <string>3662</string>
                <key>className</key>
                <string>PTModelAnimation</string>
                <key>Name</key>
                <dict>
                    <key>value</key>
                    <string></string>
                </dict>
                <key>duration</key>
                <string>0.200000</string>
                <key>animationSpeed</key>
                <string>1.000000</string>
                <key>looped</key>
                <string>0</string>
            </dict>
            <dict>
                <key>id</key>
                <string>3766</string>
                <key>className</key>
                <string>PTModelAnimation</string>
                <key>Name</key>
                <dict>
                    <key>value</key>
                    <string></string>
                </dict>
                <key>duration</key>
                <string>0.200000</string>
                <key>animationSpeed</key>
                <string>1.000000</string>
                <key>looped</key>
                <string>1</string>
            </dict>
            <dict>
                <key>id</key>
                <string>3870</string>
                <key>className</key>
                <string>PTModelAnimation</string>
                <key>Name</key>
                <dict>
                    <key>value</key>
                    <string></string>
                </dict>
                <key>duration</key>
                <string>0.366667</string>
                <key>animationSpeed</key>
                <string>1.000000</string>
                <key>looped</key>
                <string>1</string>
            </dict>
            <dict>
                <key>id</key>
                <string>3945</string>
                <key>className</key>
                <string>PTModelAnimation</string>
                <key>Name</key>
                <dict>
                    <key>value</key>
                    <string></string>
                </dict>
                <key>duration</key>
                <string>0.033333</string>
                <key>animationSpeed</key>
                <string>1.000000</string>
                <key>looped</key>
                <string>1</string>
            </dict>
            <dict>
                <key>id</key>
                <string>3959</string>
                <key>className</key>
                <string>PTModelAnimation</string>
                <key>Name</key>
                <dict>
                    <key>value</key>
                    <string></string>
                </dict>
                <key>duration</key>
                <string>0.033333</string>
                <key>animationSpeed</key>
                <string>1.000000</string>
                <key>looped</key>
                <string>1</string>
            </dict>
            <dict>
                <key>id</key>
                <string>3961</string>
                <key>className</key>
                <string>PTModelAnimation</string>
                <key>Name</key>
                <dict>
                    <key>value</key>
                    <string></string>
                </dict>
                <key>duration</key>
                <string>3.000000</string>
                <key>animationSpeed</key>
                <string>1.000000</string>
                <key>looped</key>
                <string>1</string>
            </dict>
            <dict>
                <key>id</key>
                <string>3965</string>
                <key>className</key>
                <string>PTModelAnimation</string>
                <key>Name</key>
                <dict>
                    <key>value</key>
                    <string></string>
                </dict>
                <key>duration</key>
                <string>3.000000</string>
                <key>animationSpeed</key>
                <string>1.000000</string>
                <key>looped</key>
                <string>1</string>
            </dict>
            <dict>
                <key>id</key>
                <string>4246</string>
                <key>className</key>
                <string>PTModelAnimation</string>
                <key>Name</key>
                <dict>
                    <key>value</key>
                    <string></string>
                </dict>
                <key>duration</key>
                <string>0.033333</string>
                <key>animationSpeed</key>
                <string>1.000000</string>
                <key>looped</key>
                <string>1</string>
            </dict>
            <dict>
                <key>id</key>
                <string>4606</string>
                <key>className</key>
                <string>PTModelAnimation</string>
                <key>Name</key>
                <dict>
                    <key>value</key>
                    <string></string>
                </dict>
                <key>duration</key>
                <string>0.033333</string>
                <key>animationSpeed</key>
                <string>1.000000</string>
                <key>looped</key>
                <string>1</string>
            </dict>
            <dict>
                <key>id</key>
                <string>4639</string>
                <key>className</key>
                <string>PTModelAnimation</string>
                <key>Name</key>
                <dict>
                    <key>value</key>
                    <string></string>
                </dict>
                <key>duration</key>
                <string>0.033333</string>
                <key>animationSpeed</key>
                <string>1.000000</string>
                <key>looped</key>
                <string>1</string>
            </dict>
            <dict>
                <key>id</key>
                <string>4798</string>
                <key>className</key>
                <string>PTModelAnimation</string>
                <key>Name</key>
                <dict>
                    <key>value</key>
                    <string></string>
                </dict>
                <key>duration</key>
                <string>0.033333</string>
                <key>animationSpeed</key>
                <string>1.000000</string>
                <key>looped</key>
                <string>1</string>
            </dict>
            <dict>
                <key>id</key>
                <string>4805</string>
                <key>className</key>
                <string>PTModelAnimation</string>
                <key>Name</key>
                <dict>
                    <key>value</key>
                    <string></string>
                </dict>
                <key>duration</key>
                <string>3.000000</string>
                <key>animationSpeed</key>
                <string>1.000000</string>
                <key>looped</key>
                <string>1</string>
            </dict>
            <dict>
                <key>id</key>
                <string>5018</string>
                <key>className</key>
                <string>PTModelAnimation</string>
                <key>Name</key>
                <dict>
                    <key>value</key>
                    <string></string>
                </dict>
                <key>duration</key>
                <string>3.000000</string>
                <key>animationSpeed</key>
                <string>1.000000</string>
                <key>looped</key>
                <string>1</string>
            </dict>
            <dict>
                <key>id</key>
                <string>5095</string>
                <key>className</key>
                <string>PTModelAnimation</string>
                <key>Name</key>
                <dict>
                    <key>value</key>
                    <string></string>
                </dict>
                <key>duration</key>
                <string>0.033333</string>
                <key>animationSpeed</key>
                <string>1.000000</string>
                <key>looped</key>
                <string>1</string>
            </dict>
            <dict>
                <key>id</key>
                <string>5102</string>
                <key>className</key>
                <string>PTModelAnimation</string>
                <key>Name</key>
                <dict>
                    <key>value</key>
                    <string></string>
                </dict>
                <key>duration</key>
                <string>0.033333</string>
                <key>animationSpeed</key>
                <string>1.000000</string>
                <key>looped</key>
                <string>1</string>
            </dict>
            <dict>
                <key>id</key>
                <string>5130</string>
                <key>className</key>
                <string>PTModelAnimation</string>
                <key>Name</key>
                <dict>
                    <key>value</key>
                    <string></string>
                </dict>
                <key>duration</key>
                <string>0.033333</string>
                <key>animationSpeed</key>
                <string>1.000000</string>
                <key>looped</key>
                <string>1</string>
            </dict>
            <dict>
                <key>id</key>
                <string>5166</string>
                <key>className</key>
                <string>PTModelAnimation</string>
                <key>Name</key>
                <dict>
                    <key>value</key>
                    <string></string>
                </dict>
                <key>duration</key>
                <string>3.000000</string>
                <key>animationSpeed</key>
                <string>1.000000</string>
                <key>looped</key>
                <string>1</string>
            </dict>
            <dict>
                <key>id</key>
                <string>5356</string>
                <key>className</key>
                <string>PTModelAnimation</string>
                <key>Name</key>
                <dict>
                    <key>value</key>
                    <string></string>
                </dict>
                <key>duration</key>
                <string>0.033333</string>
                <key>animationSpeed</key>
                <string>1.000000</string>
                <key>looped</key>
                <string>1</string>
            </dict>
            <dict>
                <key>id</key>
                <string>5487</string>
                <key>className</key>
                <string>PTModelAnimation</string>
                <key>Name</key>
                <dict>
                    <key>value</key>
                    <string></string>
                </dict>
                <key>duration</key>
                <string>0.466667</string>
                <key>animationSpeed</key>
                <string>1.000000</string>
                <key>looped</key>
                <string>1</string>
            </dict>
            <dict>
                <key>id</key>
                <string>5515</string>
                <key>className</key>
                <string>PTModelAnimation</string>
                <key>Name</key>
                <dict>
                    <key>value</key>
                    <string></string>
                </dict>
                <key>duration</key>
                <string>0.466667</string>
                <key>animationSpeed</key>
                <string>0.500000</string>
                <key>looped</key>
                <string>1</string>
            </dict>
            <dict>
                <key>id</key>
                <string>5583</string>
                <key>className</key>
                <string>PTModelAnimation</string>
                <key>Name</key>
                <dict>
                    <key>value</key>
                    <string></string>
                </dict>
                <key>duration</key>
                <string>0.466667</string>
                <key>animationSpeed</key>
                <string>1.000000</string>
                <key>looped</key>
                <string>1</string>
            </dict>
            <dict>
                <key>id</key>
                <string>5827</string>
                <key>className</key>
                <string>PTModelAnimation</string>
                <key>Name</key>
                <dict>
                    <key>value</key>
                    <string></string>
                </dict>
                <key>duration</key>
                <string>0.033333</string>
                <key>animationSpeed</key>
                <string>1.000000</string>
                <key>looped</key>
                <string>1</string>
            </dict>
            <dict>
                <key>id</key>
                <string>5839</string>
                <key>className</key>
                <string>PTModelAnimation</string>
                <key>Name</key>
                <dict>
                    <key>value</key>
                    <string></string>
                </dict>
                <key>duration</key>
                <string>0.033333</string>
                <key>animationSpeed</key>
                <string>1.000000</string>
                <key>looped</key>
                <string>1</string>
            </dict>
            <dict>
                <key>id</key>
                <string>6925</string>
                <key>className</key>
                <string>PTModelAnimation</string>
                <key>Name</key>
                <dict>
                    <key>value</key>
                    <string></string>
                </dict>
                <key>duration</key>
                <string>0.033333</string>
                <key>animationSpeed</key>
                <string>1.000000</string>
                <key>looped</key>
                <string>1</string>
            </dict>
            <dict>
                <key>id</key>
                <string>7495</string>
                <key>className</key>
                <string>PTModelAnimation</string>
                <key>Name</key>
                <dict>
                    <key>value</key>
                    <string></string>
                </dict>
                <key>duration</key>
                <string>0.033333</string>
                <key>animationSpeed</key>
                <string>1.000000</string>
                <key>looped</key>
                <string>1</string>
            </dict>
            <dict>
                <key>id</key>
                <string>7636</string>
                <key>className</key>
                <string>PTModelAnimation</string>
                <key>Name</key>
                <dict>
                    <key>value</key>
                    <string></string>
                </dict>
                <key>duration</key>
                <string>0.033333</string>
                <key>animationSpeed</key>
                <string>1.000000</string>
                <key>looped</key>
                <string>1</string>
            </dict>
            <dict>
                <key>id</key>
                <string>8266</string>
                <key>className</key>
                <string>PTModelAnimation</string>
                <key>Name</key>
                <dict>
                    <key>value</key>
                    <string></string>
                </dict>
                <key>duration</key>
                <string>0.033333</string>
                <key>animationSpeed</key>
                <string>1.000000</string>
                <key>looped</key>
                <string>1</string>
            </dict>
            <dict>
                <key>id</key>
                <string>8360</string>
                <key>className</key>
                <string>PTModelAnimation</string>
                <key>Name</key>
                <dict>
                    <key>value</key>
                    <string></string>
                </dict>
                <key>duration</key>
                <string>0.133333</string>
                <key>animationSpeed</key>
                <string>1.000000</string>
                <key>looped</key>
                <string>0</string>
            </dict>
            <dict>
                <key>id</key>
                <string>8458</string>
                <key>className</key>
                <string>PTModelAnimation</string>
                <key>Name</key>
                <dict>
                    <key>value</key>
                    <string></string>
                </dict>
                <key>duration</key>
                <string>0.133333</string>
                <key>animationSpeed</key>
                <string>1.000000</string>
                <key>looped</key>
                <string>1</string>
            </dict>
            <dict>
                <key>id</key>
                <string>8491</string>
                <key>className</key>
                <string>PTModelAnimation</string>
                <key>Name</key>
                <dict>
                    <key>value</key>
                    <string></string>
                </dict>
                <key>duration</key>
                <string>0.033333</string>
                <key>animationSpeed</key>
                <string>1.000000</string>
                <key>looped</key>
                <string>1</string>
            </dict>
            <dict>
                <key>id</key>
                <string>8505</string>
                <key>className</key>
                <string>PTModelAnimation</string>
                <key>Name</key>
                <dict>
                    <key>value</key>
                    <string></string>
                </dict>
                <key>duration</key>
                <string>0.033333</string>
                <key>animationSpeed</key>
                <string>1.000000</string>
                <key>looped</key>
                <string>1</string>
            </dict>
            <dict>
                <key>id</key>
                <string>8507</string>
                <key>className</key>
                <string>PTModelAnimation</string>
                <key>Name</key>
                <dict>
                    <key>value</key>
                    <string></string>
                </dict>
                <key>duration</key>
                <string>3.000000</string>
                <key>animationSpeed</key>
                <string>1.000000</string>
                <key>looped</key>
                <string>1</string>
            </dict>
            <dict>
                <key>id</key>
                <string>8511</string>
                <key>className</key>
                <string>PTModelAnimation</string>
                <key>Name</key>
                <dict>
                    <key>value</key>
                    <string></string>
                </dict>
                <key>duration</key>
                <string>3.000000</string>
                <key>animationSpeed</key>
                <string>1.000000</string>
                <key>looped</key>
                <string>1</string>
            </dict>
            <dict>
                <key>id</key>
                <string>8526</string>
                <key>className</key>
                <string>PTModelAnimation</string>
                <key>Name</key>
                <dict>
                    <key>value</key>
                    <string></string>
                </dict>
                <key>duration</key>
                <string>1.000000</string>
                <key>animationSpeed</key>
                <string>1.000000</string>
                <key>looped</key>
                <string>1</string>
            </dict>
            <dict>
                <key>id</key>
                <string>8528</string>
                <key>className</key>
                <string>PTModelAnimation</string>
                <key>Name</key>
                <dict>
                    <key>value</key>
                    <string></string>
                </dict>
                <key>duration</key>
                <string>3.000000</string>
                <key>animationSpeed</key>
                <string>1.000000</string>
                <key>looped</key>
                <string>1</string>
            </dict>
            <dict>
                <key>id</key>
                <string>8532</string>
                <key>className</key>
                <string>PTModelAnimation</string>
                <key>Name</key>
                <dict>
                    <key>value</key>
                    <string></string>
                </dict>
                <key>duration</key>
                <string>3.000000</string>
                <key>animationSpeed</key>
                <string>1.000000</string>
                <key>looped</key>
                <string>1</string>
            </dict>
            <dict>
                <key>id</key>
                <string>8639</string>
                <key>className</key>
                <string>PTModelAnimation</string>
                <key>Name</key>
                <dict>
                    <key>value</key>
                    <string></string>
                </dict>
                <key>duration</key>
                <string>1.000000</string>
                <key>animationSpeed</key>
                <string>1.000000</string>
                <key>looped</key>
                <string>1</string>
            </dict>
            <dict>
                <key>id</key>
                <string>8641</string>
                <key>className</key>
                <string>PTModelAnimation</string>
                <key>Name</key>
                <dict>
                    <key>value</key>
                    <string></string>
                </dict>
                <key>duration</key>
                <string>3.000000</string>
                <key>animationSpeed</key>
                <string>1.000000</string>
                <key>looped</key>
                <string>1</string>
            </dict>
            <dict>
                <key>id</key>
                <string>8645</string>
                <key>className</key>
                <string>PTModelAnimation</string>
                <key>Name</key>
                <dict>
                    <key>value</key>
                    <string></string>
                </dict>
                <key>duration</key>
                <string>3.000000</string>
                <key>animationSpeed</key>
                <string>1.000000</string>
                <key>looped</key>
                <string>1</string>
            </dict>
            <dict>
                <key>id</key>
                <string>8672</string>
                <key>className</key>
                <string>PTModelAnimation</string>
                <key>Name</key>
                <dict>
                    <key>value</key>
                    <string></string>
                </dict>
                <key>duration</key>
                <string>0.666667</string>
                <key>animationSpeed</key>
                <string>1.000000</string>
                <key>looped</key>
                <string>1</string>
            </dict>
            <dict>
                <key>id</key>
                <string>8674</string>
                <key>className</key>
                <string>PTModelAnimation</string>
                <key>Name</key>
                <dict>
                    <key>value</key>
                    <string></string>
                </dict>
                <key>duration</key>
                <string>3.000000</string>
                <key>animationSpeed</key>
                <string>1.000000</string>
                <key>looped</key>
                <string>1</string>
            </dict>
            <dict>
                <key>id</key>
                <string>8678</string>
                <key>className</key>
                <string>PTModelAnimation</string>
                <key>Name</key>
                <dict>
                    <key>value</key>
                    <string></string>
                </dict>
                <key>duration</key>
                <string>3.000000</string>
                <key>animationSpeed</key>
                <string>1.000000</string>
                <key>looped</key>
                <string>1</string>
            </dict>
            <dict>
                <key>id</key>
                <string>8796</string>
                <key>className</key>
                <string>PTModelAnimation</string>
                <key>Name</key>
                <dict>
                    <key>value</key>
                    <string></string>
                </dict>
                <key>duration</key>
                <string>0.033333</string>
                <key>animationSpeed</key>
                <string>1.000000</string>
                <key>looped</key>
                <string>1</string>
            </dict>
            <dict>
                <key>id</key>
                <string>8827</string>
                <key>className</key>
                <string>PTModelAnimation</string>
                <key>Name</key>
                <dict>
                    <key>value</key>
                    <string></string>
                </dict>
                <key>duration</key>
                <string>0.033333</string>
                <key>animationSpeed</key>
                <string>1.000000</string>
                <key>looped</key>
                <string>0</string>
            </dict>
            <dict>
                <key>id</key>
                <string>8847</string>
                <key>className</key>
                <string>PTModelAnimation</string>
                <key>Name</key>
                <dict>
                    <key>value</key>
                    <string></string>
                </dict>
                <key>duration</key>
                <string>0.033333</string>
                <key>animationSpeed</key>
                <string>1.000000</string>
                <key>looped</key>
                <string>1</string>
            </dict>
            <dict>
                <key>id</key>
                <string>8849</string>
                <key>className</key>
                <string>PTModelAnimation</string>
                <key>Name</key>
                <dict>
                    <key>value</key>
                    <string></string>
                </dict>
                <key>duration</key>
                <string>3.000000</string>
                <key>animationSpeed</key>
                <string>1.000000</string>
                <key>looped</key>
                <string>1</string>
            </dict>
            <dict>
                <key>id</key>
                <string>8853</string>
                <key>className</key>
                <string>PTModelAnimation</string>
                <key>Name</key>
                <dict>
                    <key>value</key>
                    <string></string>
                </dict>
                <key>duration</key>
                <string>3.000000</string>
                <key>animationSpeed</key>
                <string>1.000000</string>
                <key>looped</key>
                <string>1</string>
            </dict>
            <dict>
                <key>id</key>
                <string>9030</string>
                <key>className</key>
                <string>PTModelAnimation</string>
                <key>Name</key>
                <dict>
                    <key>value</key>
                    <string></string>
                </dict>
                <key>duration</key>
                <string>0.033333</string>
                <key>animationSpeed</key>
                <string>1.000000</string>
                <key>looped</key>
                <string>1</string>
            </dict>
            <dict>
                <key>id</key>
                <string>9032</string>
                <key>className</key>
                <string>PTModelAnimation</string>
                <key>Name</key>
                <dict>
                    <key>value</key>
                    <string></string>
                </dict>
                <key>duration</key>
                <string>0.033333</string>
                <key>animationSpeed</key>
                <string>1.000000</string>
                <key>looped</key>
                <string>0</string>
            </dict>
            <dict>
                <key>id</key>
                <string>9034</string>
                <key>className</key>
                <string>PTModelAnimation</string>
                <key>Name</key>
                <dict>
                    <key>value</key>
                    <string></string>
                </dict>
                <key>duration</key>
                <string>0.033333</string>
                <key>animationSpeed</key>
                <string>1.000000</string>
                <key>looped</key>
                <string>0</string>
            </dict>
            <dict>
                <key>id</key>
                <string>9745</string>
                <key>className</key>
                <string>PTModelAnimation</string>
                <key>Name</key>
                <dict>
                    <key>value</key>
                    <string></string>
                </dict>
                <key>duration</key>
                <string>0.033333</string>
                <key>animationSpeed</key>
                <string>1.000000</string>
                <key>looped</key>
                <string>1</string>
            </dict>
            <dict>
                <key>id</key>
                <string>9756</string>
                <key>className</key>
                <string>PTModelAnimation</string>
                <key>Name</key>
                <dict>
                    <key>value</key>
                    <string></string>
                </dict>
                <key>duration</key>
                <string>0.033333</string>
                <key>animationSpeed</key>
                <string>1.000000</string>
                <key>looped</key>
                <string>1</string>
            </dict>
            <dict>
                <key>id</key>
                <string>9767</string>
                <key>className</key>
                <string>PTModelAnimation</string>
                <key>Name</key>
                <dict>
                    <key>value</key>
                    <string></string>
                </dict>
                <key>duration</key>
                <string>0.033333</string>
                <key>animationSpeed</key>
                <string>1.000000</string>
                <key>looped</key>
                <string>1</string>
            </dict>
        </array>
    </dict>
</plist>
